MANIFEST.in
README.md
setup.cfg
setup.py
tox.ini
br_addresses/__init__.py
br_addresses/admin.py
br_addresses/choices.py
br_addresses/forms.py
br_addresses/mixins.py
br_addresses/models.py
br_addresses/signals.py
br_addresses/urls.py
br_addresses/views.py
br_addresses/migrations/0001_initial.py
br_addresses/migrations/0002_auto_20141115_2058.py
br_addresses/migrations/__init__.py
br_addresses/south_migrations/0001_initial.py
br_addresses/south_migrations/__init__.py
django_br_addresses.egg-info/PKG-INFO
django_br_addresses.egg-info/SOURCES.txt
django_br_addresses.egg-info/dependency_links.txt
django_br_addresses.egg-info/requires.txt
django_br_addresses.egg-info/top_level.txt
tests/__init__.py
tests/__init__.pyc
tests/requirements.txt
tests/runtests.py
tests/settings.py
tests/settings.pyc
tests/test_models.py
tests/test_models.pyc